testbench/TriOctDecoderDemo/vsrc/TriOctDecoderDemo.v
module TriOctDecoder(
  input        clock,
  input  [2:0] io_in,
  output [7:0] io_out
);
  reg [7:0] testReg; // @[TriOctDecoderDemo.scala 18:22]
  reg [31:0] _RAND_0;
  wire [7:0] _GEN_8; // @[TriOctDecoderDemo.scala 24:24]
  wire  _T_2; // @[Conditional.scala 37:30]
  wire [7:0] _T_4; // @[TriOctDecoderDemo.scala 29:43]
  wire  _T_5; // @[Conditional.scala 37:30]
  wire  _T_6; // @[Conditional.scala 37:30]
  wire  _T_7; // @[Conditional.scala 37:30]
  wire  _T_8; // @[Conditional.scala 37:30]
  wire  _T_9; // @[Conditional.scala 37:30]
  wire  _T_10; // @[Conditional.scala 37:30]
  wire  _T_11; // @[Conditional.scala 37:30]
  wire [7:0] _GEN_0; // @[Conditional.scala 39:67]
  wire [7:0] _GEN_1; // @[Conditional.scala 39:67]
  wire [7:0] _GEN_2; // @[Conditional.scala 39:67]
  wire [7:0] _GEN_3; // @[Conditional.scala 39:67]
  wire [7:0] _GEN_4; // @[Conditional.scala 39:67]
  wire [7:0] _GEN_5; // @[Conditional.scala 39:67]
  wire [7:0] _GEN_6; // @[Conditional.scala 39:67]
  assign _GEN_8 = {{5'd0}, io_in}; // @[TriOctDecoderDemo.scala 24:24]
  assign _T_2 = 3'h0 == io_in; // @[Conditional.scala 37:30]
  assign _T_4 = 8'h1 + testReg; // @[TriOctDecoderDemo.scala 29:43]
  assign _T_5 = 3'h1 == io_in; // @[Conditional.scala 37:30]
  assign _T_6 = 3'h2 == io_in; // @[Conditional.scala 37:30]
  assign _T_7 = 3'h3 == io_in; // @[Conditional.scala 37:30]
  assign _T_8 = 3'h4 == io_in; // @[Conditional.scala 37:30]
  assign _T_9 = 3'h5 == io_in; // @[Conditional.scala 37:30]
  assign _T_10 = 3'h6 == io_in; // @[Conditional.scala 37:30]
  assign _T_11 = 3'h7 == io_in; // @[Conditional.scala 37:30]
  assign _GEN_0 = _T_11 ? 8'h80 : 8'h0; // @[Conditional.scala 39:67]
  assign _GEN_1 = _T_10 ? 8'h40 : _GEN_0; // @[Conditional.scala 39:67]
  assign _GEN_2 = _T_9 ? 8'h20 : _GEN_1; // @[Conditional.scala 39:67]
  assign _GEN_3 = _T_8 ? 8'h10 : _GEN_2; // @[Conditional.scala 39:67]
  assign _GEN_4 = _T_7 ? 8'h8 : _GEN_3; // @[Conditional.scala 39:67]
  assign _GEN_5 = _T_6 ? 8'h4 : _GEN_4; // @[Conditional.scala 39:67]
  assign _GEN_6 = _T_5 ? 8'h2 : _GEN_5; // @[Conditional.scala 39:67]
  assign io_out = _T_2 ? _T_4 : _GEN_6; // @[TriOctDecoderDemo.scala 26:12 TriOctDecoderDemo.scala 29:20 TriOctDecoderDemo.scala 32:20 TriOctDecoderDemo.scala 35:20 TriOctDecoderDemo.scala 38:20 TriOctDecoderDemo.scala 41:20 TriOctDecoderDemo.scala 44:20 TriOctDecoderDemo.scala 47:20 TriOctDecoderDemo.scala 50:20]
`ifdef RANDOMIZE_GARBAGE_ASSIGN
`define RANDOMIZE
`endif
`ifdef RANDOMIZE_INVALID_ASSIGN
`define RANDOMIZE
`endif
`ifdef RANDOMIZE_REG_INIT
`define RANDOMIZE
`endif
`ifdef RANDOMIZE_MEM_INIT
`define RANDOMIZE
`endif
`ifndef RANDOM
`define RANDOM $random
`endif
`ifdef RANDOMIZE_MEM_INIT
  integer initvar;
`endif
`ifndef SYNTHESIS
initial begin
  `ifdef RANDOMIZE
    `ifdef INIT_RANDOM
      `INIT_RANDOM
    `endif
    `ifndef VERILATOR
      `ifdef RANDOMIZE_DELAY
        #`RANDOMIZE_DELAY begin end
      `else
        #0.002 begin end
      `endif
    `endif
  `ifdef RANDOMIZE_REG_INIT
  _RAND_0 = {1{`RANDOM}};
  testReg = _RAND_0[7:0];
  `endif // RANDOMIZE_REG_INIT
  `endif // RANDOMIZE
end // initial
`endif // SYNTHESIS
  always @(posedge clock) begin
    testReg <= testReg + _GEN_8;
  end
endmodule
module TriOctDecoderDemo(
  input        clock,
  input        reset,
  input  [2:0] io_in,
  output [7:0] io_out
);
  wire  mTriOct_clock; // @[TriOctDecoderDemo.scala 75:25]
  wire [2:0] mTriOct_io_in; // @[TriOctDecoderDemo.scala 75:25]
  wire [7:0] mTriOct_io_out; // @[TriOctDecoderDemo.scala 75:25]
  TriOctDecoder mTriOct ( // @[TriOctDecoderDemo.scala 75:25]
    .clock(mTriOct_clock),
    .io_in(mTriOct_io_in),
    .io_out(mTriOct_io_out)
  );
  assign io_out = mTriOct_io_out; // @[TriOctDecoderDemo.scala 74:12 TriOctDecoderDemo.scala 77:12]
  assign mTriOct_clock = clock;
  assign mTriOct_io_in = io_in; // @[TriOctDecoderDemo.scala 76:19]
endmodule

testbench/TriOctDecoderDemo/tb.vcd
$version Generated by VerilatedVcd $end
$date Fri Apr 10 18:16:45 2020
 $end
$timescale   1ns $end

 $scope module TOP $end
  $var wire  1 $ clock $end
  $var wire  3 & io_in [2:0] $end
  $var wire  8 ' io_out [7:0] $end
  $var wire  1 % reset $end
  $scope module TriOctDecoderDemo $end
   $var wire  1 $ clock $end
   $var wire  3 & io_in [2:0] $end
   $var wire  8 ' io_out [7:0] $end
   $var wire  1 $ mTriOct_clock $end
   $var wire  3 & mTriOct_io_in [2:0] $end
   $var wire  8 ( mTriOct_io_out [7:0] $end
   $var wire  1 % reset $end
   $scope module mTriOct $end
    $var wire  1 $ clock $end
    $var wire  3 & io_in [2:0] $end
    $var wire  8 ( io_out [7:0] $end
    $var wire  8 # testReg [7:0] $end
   $upscope $end
  $upscope $end
 $upscope $end
$enddefinitions $end


#0
b00000000 #
0$
1%
b000 &
b00000000 '
b00000001 (
#0
1$
b00000001 '
#1
0$
#2
b00000001 #
1$
b001 &
b00000010 '
b00000010 (
#3
0$
#4
b00000011 #
1$
b010 &
b00000100 '
b00000100 (
#5
0$
#6
b00000110 #
1$
b011 &
b00001000 '
b00001000 (
#7
0$
#8
b00001010 #
1$
b100 &
b00010000 '
b00010000 (
#9
0$
#10
b00001111 #
1$
b101 &
b00100000 '
b00100000 (
#11
0$
#12
b00010101 #
1$
b110 &
b01000000 '
b01000000 (
#13
0$
#14
b00011100 #
1$
b111 &
b10000000 '
b10000000 (
#15
0$
#16
b00100100 #
1$
b000 &
b00000000 '
b00000000 (
#17
0$
#18
b00101101 #
1$
b001 &
#19
0$
#20
b00110111 #
1$
b010 &
#21
0$
#22
b01000010 #
1$
b011 &
#23
0$
#24
b01001110 #
1$
b100 &
#25
0$
#26
b01011011 #
1$
b101 &
#27
0$
#28
b01101001 #
1$
b110 &
#29
0$
#30
b01111000 #
1$
b111 &
#31
0$
#32
b10001000 #
1$
b000 &
#33
0$
#34
b10011001 #
1$
b001 &
#35
0$
#36
b10101011 #
1$
b010 &
#37
0$
#38
b10111110 #
1$
b011 &
#39
0$
#40
b11010010 #
1$
b100 &
#41
0$
#42
b11100111 #
1$
b101 &
#43
0$
#44
b11111101 #
1$
b110 &
#45
0$
#46
b00010100 #
1$
b111 &
#47
0$
#48
b00101100 #
1$
b000 &
#49
0$
#50
b01000101 #
1$
b001 &
#51
0$
#52
b01011111 #
1$
b010 &
#53
0$
#54
b01111010 #
1$
b011 &
#55
0$
#56
b10010110 #
1$
b100 &
#57
0$
#58
b10110011 #
1$
b101 &
#59
0$
#60
b11010001 #
1$
b110 &
#61
0$
#62
b11110000 #
1$
b111 &
#63
0$
#64
b00010000 #
1$
b000 &
#65
0$
#66
b00110001 #
1$
b001 &
#67
0$
#68
b01010011 #
1$
b010 &
#69
0$
#70
b01110110 #
1$
b011 &
#71
0$
#72
b10011010 #
1$
b100 &
#73
0$
#74
b10111111 #
1$
b101 &
#75
0$
#76
b11100101 #
1$
b110 &
#77
0$
#78
b00001100 #
1$
b111 &
#79
0$
#80
b00110100 #
1$
b000 &
#81
0$
#82
b01011101 #
1$
b001 &
#83
0$
#84
b10000111 #
1$
b010 &
#85
0$
#86
b10110010 #
1$
b011 &
#87
0$
#88
b11011110 #
1$
b100 &
#89
0$
#90
b00001011 #
1$
b101 &
#91
0$
#92
b00111001 #
1$
b110 &
#93
0$
#94
b01101000 #
1$
b111 &
#95
0$
#96
b10011000 #
1$
b000 &
#97
0$
#98
b11001001 #
1$
b001 &
